README.md
setup.cfg
setup.py
starlog/__init__.py
starlog/compat.py
starlog/debug.py
starlog/log_entry.py
starlog/metrics.py
starlog/serializer.py
starlog/utils.py
starlog.egg-info/PKG-INFO
starlog.egg-info/SOURCES.txt
starlog.egg-info/dependency_links.txt
starlog.egg-info/requires.txt
starlog.egg-info/top_level.txt
starlog/handlers/__init__.py
starlog/handlers/base_handler.py
starlog/handlers/lookback.py
starlog/handlers/multiprocess_handler.py
starlog/handlers/status_handler.py
starlog/handlers/zmq_handler.py
tests/__init__.py
tests/conftest.py
tests/records.py
tests/test_log_entry.py
tests/test_lookback_handler.py
tests/test_metrics.py
tests/test_multiprocess_handler.py
tests/test_serializer.py
tests/test_status_handler.py
tests/test_utils.py
tests/test_zmq_handler.py
tests/handlers/__init__.py
tests/handlers/test_lookback.py