Metadata-Version: 1.1
Name: starlog
Version: 1.1.0
Summary: Sophisticated logging handlers.
Home-page: https://gitlab.com/peick/starlog
Author: Michael Peick
Author-email: michael.peick+starlog@gmail.com
License: gpl-3.0
Keywords: logging,log handler,status logging,multiprocessing,zmq
Platform: UNKNOWN
Classifier: Development Status :: 4 - Beta
Classifier: Intended Audience :: Developers
Classifier: License :: OSI Approved :: GNU General Public License v3 (GPLv3)
Classifier: Programming Language :: Python :: 2
Classifier: Programming Language :: Python :: 3
Classifier: Programming Language :: Python :: Implementation :: PyPy
Classifier: Programming Language :: Python :: Implementation :: CPython
Classifier: Topic :: System :: Logging
